[
  {
    "inputs": [
      {
        "internalType": "address[]",
        "name": "guardians_",
        "type": "address[]"
      },
      {
        "internalType": "uint256",
        "name": "threshold_",
        "type": "uint256"
      },
      {
        "internalType": "uint256",
        "name": "delay_",
        "type": "uint256"
      }
    ],
    "stateMutability": "nonpayable",
    "type": "constructor"
  },
  {
    "inputs": [],
    "name": "AlreadyApproved",
    "type": "error"
  },
  {
    "inputs": [],
    "name": "BreakGlassZeroAddress",
    "type": "error"
  },
  {
    "inputs": [],
    "name": "DelayNotElapsed",
    "type": "error"
  },
  {
    "inputs": [],
    "name": "EnforcedPause",
    "type": "error"
  },
  {
    "inputs": [],
    "name": "ExpectedPause",
    "type": "error"
  },
  {
    "inputs": [
      {
        "internalType": "address",
        "name": "account",
        "type": "address"
      },
      {
        "internalType": "uint256",
        "name": "currentNonce",
        "type": "uint256"
      }
    ],
    "name": "InvalidAccountNonce",
    "type": "error"
  },
  {
    "inputs": [],
    "name": "InvalidShortString",
    "type": "error"
  },
  {
    "inputs": [],
    "name": "InvalidThreshold",
    "type": "error"
  },
  {
    "inputs": [
      {
        "internalType": "bytes32",
        "name": "setId",
        "type": "bytes32"
      },
      {
        "internalType": "address",
        "name": "member",
        "type": "address"
      }
    ],
    "name": "MemberAlreadyExists",
    "type": "error"
  },
  {
    "inputs": [
      {
        "internalType": "bytes32",
        "name": "setId",
        "type": "bytes32"
      },
      {
        "internalType": "address",
        "name": "member",
        "type": "address"
      }
    ],
    "name": "MemberNotFound",
    "type": "error"
  },
  {
    "inputs": [],
    "name": "NotGuardian",
    "type": "error"
  },
  {
    "inputs": [
      {
        "internalType": "address",
        "name": "owner",
        "type": "address"
      }
    ],
    "name": "OwnableInvalidOwner",
    "type": "error"
  },
  {
    "inputs": [
      {
        "internalType": "address",
        "name": "account",
        "type": "address"
      }
    ],
    "name": "OwnableUnauthorizedAccount",
    "type": "error"
  },
  {
    "inputs": [],
    "name": "ProposalNotActive",
    "type": "error"
  },
  {
    "inputs": [
      {
        "internalType": "uint256",
        "name": "deadline",
        "type": "uint256"
      }
    ],
    "name": "SignedActionExpired",
    "type": "error"
  },
  {
    "inputs": [],
    "name": "SignedActionInvalidSignature",
    "type": "error"
  },
  {
    "inputs": [
      {
        "internalType": "string",
        "name": "str",
        "type": "string"
      }
    ],
    "name": "StringTooLong",
    "type": "error"
  },
  {
    "inputs": [],
    "name": "ThresholdNotMet",
    "type": "error"
  },
  {
    "inputs": [],
    "name": "ZeroDelay",
    "type": "error"
  },
  {
    "anonymous": false,
    "inputs": [
      {
        "indexed": true,
        "internalType": "address",
        "name": "sender",
        "type": "address"
      },
      {
        "indexed": false,
        "internalType": "uint256",
        "name": "amount",
        "type": "uint256"
      }
    ],
    "name": "Deposited",
    "type": "event"
  },
  {
    "anonymous": false,
    "inputs": [],
    "name": "EIP712DomainChanged",
    "type": "event"
  },
  {
    "anonymous": false,
    "inputs": [
      {
        "indexed": true,
        "internalType": "uint256",
        "name": "proposalId",
        "type": "uint256"
      },
      {
        "indexed": true,
        "internalType": "address",
        "name": "approver",
        "type": "address"
      },
      {
        "indexed": false,
        "internalType": "uint256",
        "name": "approvalCount",
        "type": "uint256"
      }
    ],
    "name": "EmergencyApproved",
    "type": "event"
  },
  {
    "anonymous": false,
    "inputs": [
      {
        "indexed": true,
        "internalType": "uint256",
        "name": "proposalId",
        "type": "uint256"
      },
      {
        "indexed": true,
        "internalType": "address",
        "name": "cancelledBy",
        "type": "address"
      }
    ],
    "name": "EmergencyCancelled",
    "type": "event"
  },
  {
    "anonymous": false,
    "inputs": [
      {
        "indexed": true,
        "internalType": "uint256",
        "name": "proposalId",
        "type": "uint256"
      },
      {
        "indexed": false,
        "internalType": "enum IBreakGlass.EmergencyAction",
        "name": "action",
        "type": "uint8"
      },
      {
        "indexed": true,
        "internalType": "address",
        "name": "executor",
        "type": "address"
      }
    ],
    "name": "EmergencyExecuted",
    "type": "event"
  },
  {
    "anonymous": false,
    "inputs": [
      {
        "indexed": true,
        "internalType": "uint256",
        "name": "proposalId",
        "type": "uint256"
      },
      {
        "indexed": true,
        "internalType": "address",
        "name": "proposer",
        "type": "address"
      },
      {
        "indexed": false,
        "internalType": "enum IBreakGlass.EmergencyAction",
        "name": "action",
        "type": "uint8"
      },
      {
        "indexed": false,
        "internalType": "address",
        "name": "target",
        "type": "address"
      },
      {
        "indexed": false,
        "internalType": "uint256",
        "name": "executeAfter",
        "type": "uint256"
      }
    ],
    "name": "EmergencyProposed",
    "type": "event"
  },
  {
    "anonymous": false,
    "inputs": [
      {
        "indexed": true,
        "internalType": "address",
        "name": "guardian",
        "type": "address"
      }
    ],
    "name": "GuardianAdded",
    "type": "event"
  },
  {
    "anonymous": false,
    "inputs": [
      {
        "indexed": true,
        "internalType": "address",
        "name": "guardian",
        "type": "address"
      }
    ],
    "name": "GuardianRemoved",
    "type": "event"
  },
  {
    "anonymous": false,
    "inputs": [
      {
        "indexed": true,
        "internalType": "bytes32",
        "name": "setId",
        "type": "bytes32"
      },
      {
        "indexed": true,
        "internalType": "address",
        "name": "member",
        "type": "address"
      }
    ],
    "name": "MemberAdded",
    "type": "event"
  },
  {
    "anonymous": false,
    "inputs": [
      {
        "indexed": true,
        "internalType": "bytes32",
        "name": "setId",
        "type": "bytes32"
      },
      {
        "indexed": true,
        "internalType": "address",
        "name": "member",
        "type": "address"
      }
    ],
    "name": "MemberRemoved",
    "type": "event"
  },
  {
    "anonymous": false,
    "inputs": [
      {
        "indexed": true,
        "internalType": "address",
        "name": "previousOwner",
        "type": "address"
      },
      {
        "indexed": true,
        "internalType": "address",
        "name": "newOwner",
        "type": "address"
      }
    ],
    "name": "OwnershipTransferred",
    "type": "event"
  },
  {
    "anonymous": false,
    "inputs": [
      {
        "indexed": false,
        "internalType": "address",
        "name": "account",
        "type": "address"
      }
    ],
    "name": "Paused",
    "type": "event"
  },
  {
    "anonymous": false,
    "inputs": [
      {
        "indexed": true,
        "internalType": "address",
        "name": "signer",
        "type": "address"
      },
      {
        "indexed": true,
        "internalType": "bytes32",
        "name": "actionHash",
        "type": "bytes32"
      },
      {
        "indexed": false,
        "internalType": "uint256",
        "name": "nonce",
        "type": "uint256"
      }
    ],
    "name": "SignedActionExecuted",
    "type": "event"
  },
  {
    "anonymous": false,
    "inputs": [
      {
        "indexed": false,
        "internalType": "address",
        "name": "account",
        "type": "address"
      }
    ],
    "name": "Unpaused",
    "type": "event"
  },
  {
    "anonymous": false,
    "inputs": [
      {
        "indexed": true,
        "internalType": "address",
        "name": "to",
        "type": "address"
      },
      {
        "indexed": false,
        "internalType": "uint256",
        "name": "amount",
        "type": "uint256"
      }
    ],
    "name": "Withdrawn",
    "type": "event"
  },
  {
    "inputs": [],
    "name": "GUARDIAN_SET",
    "outputs": [
      {
        "internalType": "bytes32",
        "name": "",
        "type": "bytes32"
      }
    ],
    "stateMutability": "view",
    "type": "function"
  },
  {
    "inputs": [],
    "name": "OPERATOR_SET",
    "outputs": [
      {
        "internalType": "bytes32",
        "name": "",
        "type": "bytes32"
      }
    ],
    "stateMutability": "view",
    "type": "function"
  },
  {
    "inputs": [],
    "name": "SIGNED_ACTION_TYPEHASH",
    "outputs": [
      {
        "internalType": "bytes32",
        "name": "",
        "type": "bytes32"
      }
    ],
    "stateMutability": "pure",
    "type": "function"
  },
  {
    "inputs": [],
    "name": "SIGNED_PAUSE_ACTION",
    "outputs": [
      {
        "internalType": "bytes32",
        "name": "",
        "type": "bytes32"
      }
    ],
    "stateMutability": "view",
    "type": "function"
  },
  {
    "inputs": [
      {
        "internalType": "address",
        "name": "guardian",
        "type": "address"
      }
    ],
    "name": "addGuardian",
    "outputs": [],
    "stateMutability": "nonpayable",
    "type": "function"
  },
  {
    "inputs": [
      {
        "internalType": "address",
        "name": "operator",
        "type": "address"
      }
    ],
    "name": "addOperator",
    "outputs": [],
    "stateMutability": "nonpayable",
    "type": "function"
  },
  {
    "inputs": [
      {
        "internalType": "uint256",
        "name": "proposalId",
        "type": "uint256"
      }
    ],
    "name": "approveEmergency",
    "outputs": [],
    "stateMutability": "nonpayable",
    "type": "function"
  },
  {
    "inputs": [
      {
        "internalType": "uint256",
        "name": "proposalId",
        "type": "uint256"
      }
    ],
    "name": "cancelEmergency",
    "outputs": [],
    "stateMutability": "nonpayable",
    "type": "function"
  },
  {
    "inputs": [],
    "name": "domainSeparator",
    "outputs": [
      {
        "internalType": "bytes32",
        "name": "",
        "type": "bytes32"
      }
    ],
    "stateMutability": "view",
    "type": "function"
  },
  {
    "inputs": [],
    "name": "eip712Domain",
    "outputs": [
      {
        "internalType": "bytes1",
        "name": "fields",
        "type": "bytes1"
      },
      {
        "internalType": "string",
        "name": "name",
        "type": "string"
      },
      {
        "internalType": "string",
        "name": "version",
        "type": "string"
      },
      {
        "internalType": "uint256",
        "name": "chainId",
        "type": "uint256"
      },
      {
        "internalType": "address",
        "name": "verifyingContract",
        "type": "address"
      },
      {
        "internalType": "bytes32",
        "name": "salt",
        "type": "bytes32"
      },
      {
        "internalType": "uint256[]",
        "name": "extensions",
        "type": "uint256[]"
      }
    ],
    "stateMutability": "view",
    "type": "function"
  },
  {
    "inputs": [
      {
        "internalType": "uint256",
        "name": "proposalId",
        "type": "uint256"
      }
    ],
    "name": "executeEmergency",
    "outputs": [],
    "stateMutability": "nonpayable",
    "type": "function"
  },
  {
    "inputs": [],
    "name": "executionDelay",
    "outputs": [
      {
        "internalType": "uint256",
        "name": "",
        "type": "uint256"
      }
    ],
    "stateMutability": "view",
    "type": "function"
  },
  {
    "inputs": [
      {
        "internalType": "uint256",
        "name": "proposalId",
        "type": "uint256"
      }
    ],
    "name": "getProposal",
    "outputs": [
      {
        "internalType": "enum IBreakGlass.EmergencyAction",
        "name": "action",
        "type": "uint8"
      },
      {
        "internalType": "address",
        "name": "target",
        "type": "address"
      },
      {
        "internalType": "address",
        "name": "proposer",
        "type": "address"
      },
      {
        "internalType": "uint256",
        "name": "approvalCount",
        "type": "uint256"
      },
      {
        "internalType": "uint256",
        "name": "thresholdMetAt",
        "type": "uint256"
      },
      {
        "internalType": "bool",
        "name": "executed",
        "type": "bool"
      },
      {
        "internalType": "bool",
        "name": "cancelled",
        "type": "bool"
      }
    ],
    "stateMutability": "view",
    "type": "function"
  },
  {
    "inputs": [],
    "name": "guardianCount",
    "outputs": [
      {
        "internalType": "uint256",
        "name": "",
        "type": "uint256"
      }
    ],
    "stateMutability": "view",
    "type": "function"
  },
  {
    "inputs": [
      {
        "internalType": "uint256",
        "name": "proposalId",
        "type": "uint256"
      },
      {
        "internalType": "address",
        "name": "guardian",
        "type": "address"
      }
    ],
    "name": "hasApproved",
    "outputs": [
      {
        "internalType": "bool",
        "name": "",
        "type": "bool"
      }
    ],
    "stateMutability": "view",
    "type": "function"
  },
  {
    "inputs": [
      {
        "internalType": "address",
        "name": "account",
        "type": "address"
      }
    ],
    "name": "isGuardian",
    "outputs": [
      {
        "internalType": "bool",
        "name": "",
        "type": "bool"
      }
    ],
    "stateMutability": "view",
    "type": "function"
  },
  {
    "inputs": [
      {
        "internalType": "bytes32",
        "name": "setId",
        "type": "bytes32"
      },
      {
        "internalType": "address",
        "name": "member",
        "type": "address"
      }
    ],
    "name": "isMember",
    "outputs": [
      {
        "internalType": "bool",
        "name": "",
        "type": "bool"
      }
    ],
    "stateMutability": "view",
    "type": "function"
  },
  {
    "inputs": [
      {
        "internalType": "bytes32",
        "name": "setId",
        "type": "bytes32"
      },
      {
        "internalType": "uint256",
        "name": "index",
        "type": "uint256"
      }
    ],
    "name": "memberAt",
    "outputs": [
      {
        "internalType": "address",
        "name": "",
        "type": "address"
      }
    ],
    "stateMutability": "view",
    "type": "function"
  },
  {
    "inputs": [
      {
        "internalType": "bytes32",
        "name": "setId",
        "type": "bytes32"
      }
    ],
    "name": "memberCount",
    "outputs": [
      {
        "internalType": "uint256",
        "name": "",
        "type": "uint256"
      }
    ],
    "stateMutability": "view",
    "type": "function"
  },
  {
    "inputs": [
      {
        "internalType": "bytes32",
        "name": "setId",
        "type": "bytes32"
      }
    ],
    "name": "members",
    "outputs": [
      {
        "internalType": "address[]",
        "name": "",
        "type": "address[]"
      }
    ],
    "stateMutability": "view",
    "type": "function"
  },
  {
    "inputs": [
      {
        "internalType": "address",
        "name": "owner",
        "type": "address"
      }
    ],
    "name": "nonces",
    "outputs": [
      {
        "internalType": "uint256",
        "name": "",
        "type": "uint256"
      }
    ],
    "stateMutability": "view",
    "type": "function"
  },
  {
    "inputs": [],
    "name": "owner",
    "outputs": [
      {
        "internalType": "address",
        "name": "",
        "type": "address"
      }
    ],
    "stateMutability": "view",
    "type": "function"
  },
  {
    "inputs": [],
    "name": "paused",
    "outputs": [
      {
        "internalType": "bool",
        "name": "",
        "type": "bool"
      }
    ],
    "stateMutability": "view",
    "type": "function"
  },
  {
    "inputs": [],
    "name": "proposalCount",
    "outputs": [
      {
        "internalType": "uint256",
        "name": "",
        "type": "uint256"
      }
    ],
    "stateMutability": "view",
    "type": "function"
  },
  {
    "inputs": [
      {
        "internalType": "enum IBreakGlass.EmergencyAction",
        "name": "action",
        "type": "uint8"
      },
      {
        "internalType": "address",
        "name": "target",
        "type": "address"
      }
    ],
    "name": "proposeEmergency",
    "outputs": [
      {
        "internalType": "uint256",
        "name": "proposalId",
        "type": "uint256"
      }
    ],
    "stateMutability": "nonpayable",
    "type": "function"
  },
  {
    "inputs": [
      {
        "internalType": "address",
        "name": "guardian",
        "type": "address"
      }
    ],
    "name": "removeGuardian",
    "outputs": [],
    "stateMutability": "nonpayable",
    "type": "function"
  },
  {
    "inputs": [
      {
        "internalType": "address",
        "name": "operator",
        "type": "address"
      }
    ],
    "name": "removeOperator",
    "outputs": [],
    "stateMutability": "nonpayable",
    "type": "function"
  },
  {
    "inputs": [],
    "name": "renounceOwnership",
    "outputs": [],
    "stateMutability": "nonpayable",
    "type": "function"
  },
  {
    "inputs": [
      {
        "internalType": "uint256",
        "name": "newThreshold",
        "type": "uint256"
      }
    ],
    "name": "setThreshold",
    "outputs": [],
    "stateMutability": "nonpayable",
    "type": "function"
  },
  {
    "inputs": [
      {
        "internalType": "address",
        "name": "signer",
        "type": "address"
      },
      {
        "internalType": "uint256",
        "name": "deadline",
        "type": "uint256"
      },
      {
        "internalType": "bytes",
        "name": "signature",
        "type": "bytes"
      }
    ],
    "name": "signedEmergencyPause",
    "outputs": [],
    "stateMutability": "nonpayable",
    "type": "function"
  },
  {
    "inputs": [],
    "name": "threshold",
    "outputs": [
      {
        "internalType": "uint256",
        "name": "",
        "type": "uint256"
      }
    ],
    "stateMutability": "view",
    "type": "function"
  },
  {
    "inputs": [
      {
        "internalType": "address",
        "name": "newOwner",
        "type": "address"
      }
    ],
    "name": "transferOwnership",
    "outputs": [],
    "stateMutability": "nonpayable",
    "type": "function"
  },
  {
    "inputs": [],
    "name": "unpause",
    "outputs": [],
    "stateMutability": "nonpayable",
    "type": "function"
  },
  {
    "inputs": [
      {
        "internalType": "address payable",
        "name": "to",
        "type": "address"
      },
      {
        "internalType": "uint256",
        "name": "amount",
        "type": "uint256"
      }
    ],
    "name": "withdraw",
    "outputs": [],
    "stateMutability": "nonpayable",
    "type": "function"
  },
  {
    "stateMutability": "payable",
    "type": "receive"
  }
]